rs/__init__.py
rs/curves.py
rs/demo.py
rs/helpers.py
rs/planner.py
rs/primitives.py
rs/unit_tests.py
rs_path-1.0.0.dist-info/LICENSE
rs_path-1.0.0.dist-info/METADATA
rs_path-1.0.0.dist-info/WHEEL
rs_path-1.0.0.dist-info/top_level.txt
rs_path-1.0.0.dist-info/RECORD
