Metadata-Version: 2.1
Name: rs-path
Version: 1.0.0
Summary: Reeds-Shepp algorithm implementation in Python
Home-page: https://github.com/builtrobotics/rs
Author: Built Robotics
Author-email: Built Robotics <tarakapoor9@gmail.com>
License: MIT License
Keywords: reeds-shepp,path,planning
Classifier: License :: OSI Approved :: MIT License
Classifier: Programming Language :: Python
Classifier: Programming Language :: Python :: 3
Requires-Python: >=3.8
License-File: LICENSE
Requires-Dist: numpy (>=1.22.4)
Provides-Extra: dev
Requires-Dist: pytest ; extra == 'dev'
